[
  {
    "full_name": "usebruno/bruno",
    "stargazers_count": 8188,
    "open_issues_count": 424,
    "forks_count": 330
  },
  {
    "full_name": "omnivore-app/omnivore",
    "stargazers_count": 6225,
    "open_issues_count": 381,
    "forks_count": 276
  },
  {
    "full_name": "achingbrain/terminatorator",
    "stargazers_count": 1,
    "open_issues_count": 0,
    "forks_count": 0
  },
  {
    "full_name": "ThePrimeagen/undefined",
    "stargazers_count": 203,
    "open_issues_count": 2,
    "forks_count": 9
  },
  {
    "full_name": "bluesky-social/social-app",
    "stargazers_count": 4270,
    "open_issues_count": 364,
    "forks_count": 582
  },
  {
    "full_name": "pingdotgg/uploadthing",
    "stargazers_count": 2858,
    "open_issues_count": 23,
    "forks_count": 177
  },
  {
    "full_name": "bluesky-social/atproto",
    "stargazers_count": 5084,
    "open_issues_count": 157,
    "forks_count": 345
  },
  {
    "full_name": "logickworkshop/Flipper-IRDB",
    "stargazers_count": 1586,
    "open_issues_count": 1,
    "forks_count": 274
  },
  {
    "full_name": "projectdiscovery/aix",
    "stargazers_count": 203,
    "open_issues_count": 8,
    "forks_count": 16
  },
  {
    "full_name": "projectdiscovery/cloudlist",
    "stargazers_count": 712,
    "open_issues_count": 6,
    "forks_count": 99
  },
  {
    "full_name": "projectdiscovery/nuclei-templates",
    "stargazers_count": 7273,
    "open_issues_count": 144,
    "forks_count": 2232
  },
  {
    "full_name": "lukevella/rallly",
    "stargazers_count": 2638,
    "open_issues_count": 17,
    "forks_count": 248
  },
  {
    "full_name": "projectdiscovery/pdtm",
    "stargazers_count": 572,
    "open_issues_count": 6,
    "forks_count": 43
  },
  {
    "full_name": "projectdiscovery/subfinder",
    "stargazers_count": 8499,
    "open_issues_count": 11,
    "forks_count": 1143
  },
  {
    "full_name": "projectdiscovery/openrisk",
    "stargazers_count": 153,
    "open_issues_count": 4,
    "forks_count": 18
  },
  {
    "full_name": "meltano/meltano",
    "stargazers_count": 1362,
    "open_issues_count": 447,
    "forks_count": 127
  },
  {
    "full_name": "projectdiscovery/katana",
    "stargazers_count": 7678,
    "open_issues_count": 62,
    "forks_count": 409
  },
  {
    "full_name": "fauxpilot/fauxpilot",
    "stargazers_count": 13466,
    "open_issues_count": 64,
    "forks_count": 592
  },
  {
    "full_name": "slsa-framework/slsa",
    "stargazers_count": 1308,
    "open_issues_count": 154,
    "forks_count": 198
  },
  {
    "full_name": "t3-oss/create-t3-app",
    "stargazers_count": 21220,
    "open_issues_count": 42,
    "forks_count": 924
  },
  {
    "full_name": "sigstore/cosign",
    "stargazers_count": 3739,
    "open_issues_count": 211,
    "forks_count": 469
  },
  {
    "full_name": "josephernest/writing",
    "stargazers_count": 1008,
    "open_issues_count": 15,
    "forks_count": 82
  },
  {
    "full_name": "umami-software/umami",
    "stargazers_count": 17496,
    "open_issues_count": 76,
    "forks_count": 3218
  },
  {
    "full_name": "JohnEdChristensen/WebbCompare",
    "stargazers_count": 409,
    "open_issues_count": 8,
    "forks_count": 29
  },
  {
    "full_name": "honkit/honkit",
    "stargazers_count": 2751,
    "open_issues_count": 58,
    "forks_count": 207
  },
  {
    "full_name": "troxler/awesome-css-frameworks",
    "stargazers_count": 6707,
    "open_issues_count": 4,
    "forks_count": 407
  },
  {
    "full_name": "boltgolt/howdy",
    "stargazers_count": 5010,
    "open_issues_count": 183,
    "forks_count": 281
  },
  {
    "full_name": "opencast/opencast",
    "stargazers_count": 353,
    "open_issues_count": 221,
    "forks_count": 221
  },
  {
    "full_name": "Guake/guake",
    "stargazers_count": 4275,
    "open_issues_count": 384,
    "forks_count": 620
  },
  {
    "full_name": "tailscale/tailscale",
    "stargazers_count": 14242,
    "open_issues_count": 1667,
    "forks_count": 1055
  }
]